django_filtering/__init__.py
django_filtering/conf.py
django_filtering/filters.py
django_filtering/filterset.py
django_filtering/form.py
django_filtering/schema.py
django_filtering/utils.py
django_filtering-0.3.2.dist-info/METADATA
django_filtering-0.3.2.dist-info/WHEEL
django_filtering-0.3.2.dist-info/licenses/LICENSE
django_filtering-0.3.2.dist-info/RECORD
