Metadata-Version: 2.4
Name: django-filtering
Version: 0.3.2
Summary: Allows users to filter Django models
Project-URL: Homepage, https://github.com/The-Shadowserver-Foundation/django-filtering
Project-URL: Issues, https://github.com/The-Shadowserver-Foundation/django-filtering/issues
Author: The Shadowserver Foundation
Author-email: Michael Mulich <michael@mulich.com>
License-Expression: GPL-3.0
License-File: LICENSE
Classifier: Framework :: Django
Classifier: Framework :: Django :: 4
Classifier: Framework :: Django :: 5
Classifier: Operating System :: OS Independent
Classifier: Programming Language :: Python :: 3
Requires-Python: >=3.8
Requires-Dist: django>=4.2
Requires-Dist: jsonschema
Provides-Extra: tests
Requires-Dist: ipdb; extra == 'tests'
Requires-Dist: model-bakery; extra == 'tests'
Requires-Dist: pytest; extra == 'tests'
Requires-Dist: pytest-django; extra == 'tests'
